setup.py
brynq_sdk_abacus/__init__.py
brynq_sdk_abacus/abacus_interface.py
brynq_sdk_abacus.egg-info/PKG-INFO
brynq_sdk_abacus.egg-info/SOURCES.txt
brynq_sdk_abacus.egg-info/dependency_links.txt
brynq_sdk_abacus.egg-info/not-zip-safe
brynq_sdk_abacus.egg-info/requires.txt
brynq_sdk_abacus.egg-info/top_level.txt