Metadata-Version: 1.0
Name: brynq-sdk-abacus
Version: 1.0.5
Summary: Abacus wrapper from BrynQ
Home-page: UNKNOWN
Author: BrynQ
Author-email: support@brynq.com
License: BrynQ License
Platform: UNKNOWN
